libcv/__init__.py
libcv/facealignment.py
libcv/facebeautify.py
libcv/facedetect.py
libcv/facemorph.py
libcv/gabor_filter.py
libcv/loss_log.txt
libcv/requirement.txt
libcv/tri_order.txt
libcv/video_tool.py
libcv/vis_loss.py
libcv/vis_loss.txt
libcv/comm/__init__.py
libcv/comm/cross_point.py
libcv/comm/distribution.py
libcv/comm/gabor_filter.py
libcv/comm/io_util.py
libcv/comm/mypdf.py
libcv/comm/myzipfile.py
libcv/comm/poly_iou.py
libcv/detection/__init__.py
libcv/detection/core.py
libcv/detection/utils.py
libcv/detection/dlib/__init__.py
libcv/detection/dlib/dlib_detector.py
libcv/detection/facebox/FaceBoxes.py
libcv/detection/facebox/FaceBoxes_ONNX.py
libcv/detection/facebox/__init__.py
libcv/detection/facebox/onnx.py
libcv/detection/facebox/models/__init__.py
libcv/detection/facebox/models/faceboxes.py
libcv/detection/facebox/utils/__init__.py
libcv/detection/facebox/utils/box_utils.py
libcv/detection/facebox/utils/build.py
libcv/detection/facebox/utils/config.py
libcv/detection/facebox/utils/functions.py
libcv/detection/facebox/utils/nms_wrapper.py
libcv/detection/facebox/utils/prior_box.py
libcv/detection/facebox/utils/timer.py
libcv/detection/facebox/utils/nms/__init__.py
libcv/detection/facebox/utils/nms/py_cpu_nms.py
libcv/detection/facebox/weights/FaceBoxesProd.pth
libcv/detection/folder/__init__.py
libcv/detection/folder/folder_detector.py
libcv/detection/retina/__init__.py
libcv/detection/retina/_version.py
libcv/detection/retina/alignment.py
libcv/detection/retina/detector.py
libcv/detection/retina/weights/mobilenet0.25_Final.pth
libcv/detection/sfd/__init__.py
libcv/detection/sfd/bbox.py
libcv/detection/sfd/detect.py
libcv/detection/sfd/net_s3fd.py
libcv/detection/sfd/sfd_detector.py
libcv/voice/__init__.py
libcv-0.0.1.dist-info/LICENSE
libcv-0.0.1.dist-info/METADATA
libcv-0.0.1.dist-info/WHEEL
libcv-0.0.1.dist-info/top_level.txt
libcv-0.0.1.dist-info/RECORD
